.coveragerc
.gitignore
.travis.yml
CHANGELOG.rst
LICENSE
MANIFEST.in
Makefile
README.rst
requirements.txt
setup.cfg
setup.py
tox.ini
docs/Makefile
docs/changelog.rst
docs/conf.py
docs/index.rst
docs/jwalk.rst
docs/make.bat
docs/modules.rst
docs/overview.rst
docs/images/jwalk_logo.gif
jwalk/__init__.py
jwalk/__main__.py
jwalk/corpus.py
jwalk/graph.py
jwalk/io.py
jwalk/skipgram.py
jwalk.egg-info/PKG-INFO
jwalk.egg-info/SOURCES.txt
jwalk.egg-info/dependency_links.txt
jwalk.egg-info/entry_points.txt
jwalk.egg-info/not-zip-safe
jwalk.egg-info/requires.txt
jwalk.egg-info/top_level.txt
jwalk/src/walks.c
jwalk/src/walks.pyx
tests/test_jwalk.py
tests/__pycache__/test_jwalk.cpython-27-PYTEST.pyc
tests/__pycache__/test_jwalk.cpython-34-PYTEST.pyc
tests/data/corpus.txt.gzip
tests/data/karate.edgelist
tests/data/karate.embeddings
tests/data/karate.npz