Metadata-Version: 1.1
Name: jwalk
Version: 0.5.3
Summary: Representational learning on graphs
Home-page: https://github.com/jwplayer/jwalk
Author: Kamil Sindi, Nir Yungster
Author-email: kamil@jwplayer.com, nir@jwplayer.com
License: Apache License 2.0
Keywords: deep learning,neural networks,deepwalk
Platform: UNKNOWN
Classifier: Development Status :: 4 - Beta
Classifier: Intended Audience :: Science/Research
Classifier: License :: OSI Approved :: Apache Software License
Classifier: Environment :: Console
Classifier: Programming Language :: Python :: 2
Classifier: Programming Language :: Python :: 2.7
Classifier: Programming Language :: Python :: 3
Classifier: Programming Language :: Python :: 3.4
Classifier: Programming Language :: Python :: 3.5
Classifier: Programming Language :: Python :: 3.6
Classifier: Programming Language :: Cython
Classifier: Topic :: Scientific/Engineering
